geoletrld/__init__.py
geoletrld/distances/CaGeoDistance.py
geoletrld/distances/DistanceInterface.py
geoletrld/distances/EuclideanDistance.py
geoletrld/distances/FrechetDistance.py
geoletrld/distances/InterpolatedTimeDistance.py
geoletrld/distances/LCSSTrajectoryDistance.py
geoletrld/distances/MatchComputeDistance.py
geoletrld/distances/RotatingGenericDistance.py
geoletrld/distances/_DistancesUtils.py
geoletrld/distances/__init__.py
geoletrld/model/Geolet.py
geoletrld/model/__init__.py
geoletrld/partitioners/FeaturePartitioner.py
geoletrld/partitioners/GeohashPartitioner.py
geoletrld/partitioners/NoPartitioner.py
geoletrld/partitioners/PartitionerInterface.py
geoletrld/partitioners/SlidingWindowPartitioner.py
geoletrld/partitioners/__init__.py
geoletrld/selectors/ClusteringSelector.py
geoletrld/selectors/GapSelector.py
geoletrld/selectors/MutualInformationSelector.py
geoletrld/selectors/RandomSelector.py
geoletrld/selectors/SelectorInterface.py
geoletrld/selectors/SelectorPipeline.py
geoletrld/selectors/_SelectorUtils.py
geoletrld/selectors/__init__.py
geoletrld/utils/Trajectories.py
geoletrld/utils/Trajectory.py
geoletrld/utils/__init__.py
geoletrld/utils/data_preparation.py
geolet_reloaded-0.0.3.dist-info/LICENSE
geolet_reloaded-0.0.3.dist-info/METADATA
geolet_reloaded-0.0.3.dist-info/WHEEL
geolet_reloaded-0.0.3.dist-info/top_level.txt
geolet_reloaded-0.0.3.dist-info/RECORD
