Metadata-Version: 2.2
Name: geolet-reloaded
Version: 0.0.3
Summary: Package description
Home-page: https://github.com/cri98li/Geolet-reloaded
Author: Cristiano Landi
Author-email: cristiano.landi@phd.unipi.it
License: BSD-Clause-2
Keywords: keyword1 keyword2 keyword3
Classifier: Development Status :: 4 - Beta
Classifier: Intended Audience :: Developers
Classifier: Topic :: Software Development :: Build Tools
Classifier: License :: OSI Approved :: BSD License
Classifier: Operating System :: POSIX :: Other
Classifier: Operating System :: MacOS
Classifier: Programming Language :: Python
Classifier: Programming Language :: Python :: 3
License-File: LICENSE
Requires-Dist: mock
Requires-Dist: setuptools
Requires-Dist: numpy~=1.26.4
Requires-Dist: geolib
Requires-Dist: pandas
Requires-Dist: scikit-learn
Requires-Dist: tqdm
Requires-Dist: torch
Requires-Dist: tsaug
Requires-Dist: tslearn
Requires-Dist: h5py
Requires-Dist: cageo
Requires-Dist: TrajectoryIntervalForest
Requires-Dist: scikit-learn-extra
Requires-Dist: similaritymeasures
Provides-Extra: flag
Dynamic: author
Dynamic: author-email
Dynamic: classifier
Dynamic: description
Dynamic: description-content-type
Dynamic: home-page
Dynamic: keywords
Dynamic: license
Dynamic: provides-extra
Dynamic: requires-dist
Dynamic: summary
